sigProfilerPlotting/__init__.py
sigProfilerPlotting/plotActivity.py
sigProfilerPlotting/sample_portrait.py
sigProfilerPlotting/sigProfilerPlotting.py
sigProfilerPlotting/sigProfilerPlotting_CLI.py
sigProfilerPlotting/sigProfilerPlotting_old.py
sigProfilerPlotting/tmbplot.py
sigProfilerPlotting/version.py
sigProfilerPlotting/controllers/__init__.py
sigProfilerPlotting/controllers/cli_controller.py
sigProfilerPlotting/fonts/Arial Bold.ttf
sigProfilerPlotting/fonts/Arial.ttf
sigProfilerPlotting/fonts/Courier New Bold.ttf
sigProfilerPlotting/fonts/Courier New.ttf
sigProfilerPlotting/fonts/Times New Roman Bold.ttf
sigProfilerPlotting/fonts/Times New Roman.ttf
sigProfilerPlotting/fonts/__init__.py
sigProfilerPlotting/reference_formats/CNV48.txt
sigProfilerPlotting/reference_formats/DBS1248.txt
sigProfilerPlotting/reference_formats/DBS150.txt
sigProfilerPlotting/reference_formats/DBS186.txt
sigProfilerPlotting/reference_formats/DBS2400.txt
sigProfilerPlotting/reference_formats/DBS2976.txt
sigProfilerPlotting/reference_formats/DBS78.txt
sigProfilerPlotting/reference_formats/ID28.txt
sigProfilerPlotting/reference_formats/ID332.txt
sigProfilerPlotting/reference_formats/ID415.txt
sigProfilerPlotting/reference_formats/ID83.txt
sigProfilerPlotting/reference_formats/ID8628.txt
sigProfilerPlotting/reference_formats/ID96.txt
sigProfilerPlotting/reference_formats/SBS1536.txt
sigProfilerPlotting/reference_formats/SBS18.txt
sigProfilerPlotting/reference_formats/SBS24.txt
sigProfilerPlotting/reference_formats/SBS288.txt
sigProfilerPlotting/reference_formats/SBS384.txt
sigProfilerPlotting/reference_formats/SBS4608.txt
sigProfilerPlotting/reference_formats/SBS6.txt
sigProfilerPlotting/reference_formats/SBS6144.txt
sigProfilerPlotting/reference_formats/SBS96.txt
sigProfilerPlotting/reference_formats/SV32.txt
sigprofilerplotting-1.4.2.dist-info/licenses/LICENSE
sigprofilerplotting-1.4.2.dist-info/METADATA
sigprofilerplotting-1.4.2.dist-info/WHEEL
sigprofilerplotting-1.4.2.dist-info/entry_points.txt
sigprofilerplotting-1.4.2.dist-info/top_level.txt
sigprofilerplotting-1.4.2.dist-info/RECORD
