Metadata-Version: 2.4
Name: sigProfilerPlotting
Version: 1.4.2
Summary: SigProfiler plotting tool
Home-page: https://github.com/alexandrovlab/SigProfilerPlotting
Author: Erik Bergstrom
Author-email: ebergstr@eng.ucsd.edu
License: UCSD
Requires-Python: >=3.9
License-File: LICENSE
Requires-Dist: matplotlib>=3.4.3
Requires-Dist: pandas>=2.0.0
Requires-Dist: scikit-learn>=1.1.3
Requires-Dist: pillow>=10.0.0
Provides-Extra: tests
Requires-Dist: pytest; extra == "tests"
Requires-Dist: scikit-image>=0.21.0; extra == "tests"
Requires-Dist: numpy>=2.0.0; extra == "tests"
Dynamic: author
Dynamic: author-email
Dynamic: description
Dynamic: description-content-type
Dynamic: home-page
Dynamic: license
Dynamic: license-file
Dynamic: provides-extra
Dynamic: requires-dist
Dynamic: requires-python
Dynamic: summary
